{
  "name": "Base16 Dark Unikitty",
  "type": "light",
  "colors": {
    "editor.background": "#ffffff",
    "editor.foreground": "#6c696e",
    "editor.selectionBackground": "#c4c3c5",
    "editor.lineHighlightBackground": "#a7a5a855",
    "editorCursor.foreground": "#6c696e",
    "editorWhitespace.foreground": "#a7a5a8"
  },
  "tokenColors": [
    {
      "settings": {
        "foreground": "#6c696eff",
        "background": "#ffffffff"
      }
    },
    {
      "name": "Text",
      "scope": "variable.parameter.function",
      "settings": {
        "foreground": "#6c696e"
      }
    },
    {
      "name": "Comments",
      "scope": "comment, punctuation.definition.comment",
      "settings": {
        "foreground": "#a7a5a8"
      }
    },
    {
      "name": "Punctuation",
      "scope": "punctuation.definition.string, punctuation.definition.variable, punctuation.definition.string, punctuation.definition.parameters, punctuation.definition.string, punctuation.definition.array",
      "settings": {
        "foreground": "#6c696e"
      }
    },
    {
      "name": "Delimiters",
      "scope": "none",
      "settings": {
        "foreground": "#6c696e"
      }
    },
    {
      "name": "Operators",
      "scope": "keyword.operator",
      "settings": {
        "foreground": "#6c696e"
      }
    },
    {
      "name": "Keywords",
      "scope": "keyword",
      "settings": {
        "foreground": "#aa17e6"
      }
    },
    {
      "name": "Variables",
      "scope": "variable",
      "settings": {
        "foreground": "#d8137f"
      }
    },
    {
      "name": "Functions",
      "scope": "entity.name.function, meta.require, support.function.any-method",
      "settings": {
        "foreground": "#775dff"
      }
    },
    {
      "name": "Classes",
      "scope": "support.class, entity.name.class, entity.name.type.class",
      "settings": {
        "foreground": "#dc8a0e"
      }
    },
    {
      "name": "Classes",
      "scope": "meta.class",
      "settings": {
        "foreground": "#322d34"
      }
    },
    {
      "name": "Methods",
      "scope": "keyword.other.special-method",
      "settings": {
        "foreground": "#775dff"
      }
    },
    {
      "name": "Storage",
      "scope": "storage",
      "settings": {
        "foreground": "#aa17e6"
      }
    },
    {
      "name": "Support",
      "scope": "support.function",
      "settings": {
        "foreground": "#149bda"
      }
    },
    {
      "name": "Strings, Inherited Class",
      "scope": "string, constant.other.symbol, entity.other.inherited-class",
      "settings": {
        "foreground": "#17ad98"
      }
    },
    {
      "name": "Integers",
      "scope": "constant.numeric",
      "settings": {
        "foreground": "#d65407"
      }
    },
    {
      "name": "Floats",
      "scope": "none",
      "settings": {
        "foreground": "#d65407"
      }
    },
    {
      "name": "Boolean",
      "scope": "none",
      "settings": {
        "foreground": "#d65407"
      }
    },
    {
      "name": "Constants",
      "scope": "constant",
      "settings": {
        "foreground": "#d65407"
      }
    },
    {
      "name": "Tags",
      "scope": "entity.name.tag",
      "settings": {
        "foreground": "#d8137f"
      }
    },
    {
      "name": "Attributes",
      "scope": "entity.other.attribute-name",
      "settings": {
        "foreground": "#d65407"
      }
    },
    {
      "name": "Attribute IDs",
      "scope": "entity.other.attribute-name.id, punctuation.definition.entity",
      "settings": {
        "foreground": "#775dff"
      }
    },
    {
      "name": "Selector",
      "scope": "meta.selector",
      "settings": {
        "foreground": "#aa17e6"
      }
    },
    {
      "name": "Values",
      "scope": "none",
      "settings": {
        "foreground": "#d65407"
      }
    },
    {
      "name": "Headings",
      "scope": "markup.heading punctuation.definition.heading, entity.name.section",
      "settings": {
        "fontStyle": "",
        "foreground": "#775dff"
      }
    },
    {
      "name": "Units",
      "scope": "keyword.other.unit",
      "settings": {
        "foreground": "#d65407"
      }
    },
    {
      "name": "Bold",
      "scope": "markup.bold, punctuation.definition.bold",
      "settings": {
        "fontStyle": "bold",
        "foreground": "#dc8a0e"
      }
    },
    {
      "name": "Italic",
      "scope": "markup.italic, punctuation.definition.italic",
      "settings": {
        "fontStyle": "italic",
        "foreground": "#aa17e6"
      }
    },
    {
      "name": "Code",
      "scope": "markup.raw.inline",
      "settings": {
        "foreground": "#17ad98"
      }
    },
    {
      "name": "Link Text",
      "scope": "string.other.link, punctuation.definition.string.end.markdown",
      "settings": {
        "foreground": "#d8137f"
      }
    },
    {
      "name": "Link Url",
      "scope": "meta.link",
      "settings": {
        "foreground": "#d65407"
      }
    },
    {
      "name": "Lists",
      "scope": "markup.list",
      "settings": {
        "foreground": "#d8137f"
      }
    },
    {
      "name": "Quotes",
      "scope": "markup.quote",
      "settings": {
        "foreground": "#d65407"
      }
    },
    {
      "name": "Separator",
      "scope": "meta.separator",
      "settings": {
        "background": "#c4c3c5",
        "foreground": "#6c696e"
      }
    },
    {
      "name": "Inserted",
      "scope": "markup.inserted",
      "settings": {
        "foreground": "#17ad98"
      }
    },
    {
      "name": "Deleted",
      "scope": "markup.deleted",
      "settings": {
        "foreground": "#d8137f"
      }
    },
    {
      "name": "Changed",
      "scope": "markup.changed",
      "settings": {
        "foreground": "#aa17e6"
      }
    },
    {
      "name": "Colors",
      "scope": "constant.other.color",
      "settings": {
        "foreground": "#149bda"
      }
    },
    {
      "name": "Regular Expressions",
      "scope": "string.regexp",
      "settings": {
        "foreground": "#149bda"
      }
    },
    {
      "name": "Escape Characters",
      "scope": "constant.character.escape",
      "settings": {
        "foreground": "#149bda"
      }
    },
    {
      "name": "Embedded",
      "scope": "punctuation.section.embedded, variable.interpolation",
      "settings": {
        "foreground": "#aa17e6"
      }
    },
    {
      "name": "Illegal",
      "scope": "invalid.illegal",
      "settings": {
        "background": "#d8137f",
        "foreground": "#322d34"
      }
    },
    {
      "name": "Broken",
      "scope": "invalid.broken",
      "settings": {
        "background": "#d65407",
        "foreground": "#ffffff"
      }
    },
    {
      "name": "Deprecated",
      "scope": "invalid.deprecated",
      "settings": {
        "background": "#e013d0",
        "foreground": "#322d34"
      }
    },
    {
      "name": "Unimplemented",
      "scope": "invalid.unimplemented",
      "settings": {
        "background": "#a7a5a8",
        "foreground": "#322d34"
      }
    },
    {
      "scope": "token.info-token",
      "settings": {
        "foreground": "#316bcd"
      }
    },
    {
      "scope": "token.warn-token",
      "settings": {
        "foreground": "#cd9731"
      }
    },
    {
      "scope": "token.error-token",
      "settings": {
        "foreground": "#cd3131"
      }
    },
    {
      "scope": "token.debug-token",
      "settings": {
        "foreground": "#800080"
      }
    }
  ]
}